ADFWI/__init__.py
ADFWI/dip/__init__.py
ADFWI/dip/dip_acoustic_fwi.py
ADFWI/dip/dip_acoustic_model.py
ADFWI/dip/dip_acoustic_model_vp_rho.py
ADFWI/dip/dip_elastic_fwi.py
ADFWI/dip/dip_elastic_model.py
ADFWI/dip/dip_elastic_model_vp_vs.py
ADFWI/dip/dip_elastic_model_vp_vs_rho.py
ADFWI/dip/dip_vti_model.py
ADFWI/dip/dip_vti_model_o4a.py
ADFWI/dip/model/CNN.py
ADFWI/dip/model/MLP.py
ADFWI/dip/model/MobileNetV2.py
ADFWI/dip/model/ResNet.py
ADFWI/dip/model/Unet.py
ADFWI/dip/model/__init__.py
ADFWI/dip/model2/CNN.py
ADFWI/dip/model2/CNN_2stream.py
ADFWI/dip/model2/KAN.py
ADFWI/dip/model2/MLP.py
ADFWI/dip/model2/__init__.py
ADFWI/dip/model3/CNN.py
ADFWI/dip/model3/MLP.py
ADFWI/dip/model3/__init__.py
ADFWI/dip/model4/CNN.py
ADFWI/dip/model4/MLP.py
ADFWI/dip/model4/__init__.py
ADFWI/dip/model_multi/CNN.py
ADFWI/dip/model_multi/MLP.py
ADFWI/dip/model_multi/__init__.py
ADFWI/fwi/__init__.py
ADFWI/fwi/acoustic_fwi.py
ADFWI/fwi/elastic_fwi.py
ADFWI/fwi/multiScaleProcessing.py
ADFWI/fwi/misfit/Envelope.py
ADFWI/fwi/misfit/GlobalCorrelation.py
ADFWI/fwi/misfit/L1.py
ADFWI/fwi/misfit/L2.py
ADFWI/fwi/misfit/Normalized_Integration_method.py
ADFWI/fwi/misfit/SmoothL1.py
ADFWI/fwi/misfit/SoftDTW.py
ADFWI/fwi/misfit/StudentT.py
ADFWI/fwi/misfit/TravelTime.py
ADFWI/fwi/misfit/WDGC.py
ADFWI/fwi/misfit/Wasserstein_1.py
ADFWI/fwi/misfit/Wasserstein_1d.py
ADFWI/fwi/misfit/Wasserstein_sinkhorn.py
ADFWI/fwi/misfit/Weci.py
ADFWI/fwi/misfit/Weighted_L1_L2.py
ADFWI/fwi/misfit/__init__.py
ADFWI/fwi/misfit/base.py
ADFWI/fwi/optimizer/__init__.py
ADFWI/fwi/optimizer/optimizer_swit.py
ADFWI/fwi/regularization/__init__.py
ADFWI/fwi/regularization/base.py
ADFWI/fwi/regularization/tikhonov_1order.py
ADFWI/fwi/regularization/tikhonov_2order.py
ADFWI/fwi/regularization/tv_1order.py
ADFWI/fwi/regularization/tv_2order.py
ADFWI/model/__init__.py
ADFWI/model/acoustic_model.py
ADFWI/model/base.py
ADFWI/model/elastic_model.py
ADFWI/model/parameters.py
ADFWI/propagator/__init__.py
ADFWI_Torch-0.1.2.dist-info/LICENSE
ADFWI_Torch-0.1.2.dist-info/METADATA
ADFWI_Torch-0.1.2.dist-info/WHEEL
ADFWI_Torch-0.1.2.dist-info/top_level.txt
ADFWI_Torch-0.1.2.dist-info/RECORD
