Metadata-Version: 2.1
Name: ADFWI-Torch
Version: 0.1.2
Summary: ADFWI: A framework for high-resolution subsurface parameter estimation using Full Waveform Inversion
Home-page: https://github.com/liufeng2317/ADFWI
Author: Feng Liu
Author-email: liufeng2317@sjtu.edu.cn
License: MIT
Classifier: Programming Language :: Python :: 3
Classifier: License :: OSI Approved :: MIT License
Classifier: Operating System :: OS Independent
Classifier: Intended Audience :: Science/Research
Classifier: Programming Language :: Python :: 3.8
Classifier: Programming Language :: Python :: 3.9
License-File: LICENSE
Requires-Dist: numpy >=1.24.0
Requires-Dist: scipy >=1.10.0
Requires-Dist: matplotlib >=3.7.0
Requires-Dist: torch >=2.0.0
Requires-Dist: disba >=0.6.0
Requires-Dist: torchinfo
Requires-Dist: segyio
Requires-Dist: ncg-optimizer
Requires-Dist: pysdtw
Requires-Dist: geomloss
Requires-Dist: h5py
Requires-Dist: obspy
Requires-Dist: tqdm
Requires-Dist: FyeldGenerator
